conflkv/__init__.py
conflkv/py.typed
conflkv-0.0.3.dist-info/METADATA
conflkv-0.0.3.dist-info/WHEEL
conflkv-0.0.3.dist-info/RECORD
