Metadata-Version: 2.3
Name: conflKV
Version: 0.0.3
Summary: ConflKV is a Python library for managing key-value pairs stored in Confluence Pages through the REST API.
Author-email: David Moruzzi <confl.kv@dmoruzi.com>
Keywords: confluence,key-value
Classifier: Development Status :: 3 - Alpha
Classifier: Intended Audience :: Developers
Classifier: Programming Language :: Python :: 3.12
Classifier: Programming Language :: Python :: 3.13
Classifier: Topic :: Software Development :: Libraries :: Python Modules
Requires-Python: >=3.12
